electron_inject/__init__.py
electron_inject/__main__.py
electron_inject-0.6.dist-info/METADATA
electron_inject-0.6.dist-info/WHEEL
electron_inject-0.6.dist-info/top_level.txt
electron_inject-0.6.dist-info/RECORD
