Metadata-Version: 2.1
Name: electron-inject
Version: 0.6
Summary: An electron application wrapper that utilizes the remote debug console to inject code into electron applications to enable developer tools
Home-page: https://github.com/tintinweb/electron-inject/
Author: tintinweb
Author-email: tintinweb@oststrom.com
License: GPLv3
Download-URL: https://github.com/tintinweb/electron-inject/tarball/v0.5
Keywords: electron,inject,devtools,developer tools
Platform: UNKNOWN
Requires-Dist: websocket
Requires-Dist: requests
